MANIFEST.in
setup.py
django_ffiler/LICENSE
django_ffiler/README.md
django_ffiler/__init__.py
django_ffiler/admin.py
django_ffiler/urls.py
django_ffiler/views.py
django_ffiler.egg-info/PKG-INFO
django_ffiler.egg-info/SOURCES.txt
django_ffiler.egg-info/dependency_links.txt
django_ffiler.egg-info/top_level.txt
django_ffiler/static/ffiler/css/bootstrap.css
django_ffiler/static/ffiler/css/ffiler.css
django_ffiler/static/ffiler/css/magnific-popup.css
django_ffiler/static/ffiler/fonts/glyphicons-halflings-regular.eot
django_ffiler/static/ffiler/fonts/glyphicons-halflings-regular.svg
django_ffiler/static/ffiler/fonts/glyphicons-halflings-regular.ttf
django_ffiler/static/ffiler/fonts/glyphicons-halflings-regular.woff
django_ffiler/static/ffiler/js/bootstrap.js
django_ffiler/static/ffiler/js/bootstrap.min.js
django_ffiler/static/ffiler/js/django_transport.js
django_ffiler/static/ffiler/js/ffiler.js
django_ffiler/static/ffiler/js/jq.2.0.3.js
django_ffiler/static/ffiler/js/jquery.magnific-popup.min.js
django_ffiler/templates/admin/edit_inline/ffiler.html