Metadata-Version: 1.1
Name: django-ffiler
Version: 0.1
Summary: Django admin inline images + multiupload. 
Home-page: https://github.com/xacce/django_ffiler
Author: Anton
Author-email: thisice@gmail.com
License: MIT License
Download-URL: https://github.com/xacce/django_ffiler/archive/master.zip
Keywords: django,multiupload,admin
Platform: UNKNOWN
Classifier: Environment :: Web Environment
Classifier: Framework :: Django
Classifier: Intended Audience :: Developers
Classifier: Programming Language :: Python
Requires: python (>= 2.5)
Requires: django (<= 1.5)
